pypicosdk/README.md
pypicosdk/__init__.py
pypicosdk/base.py
pypicosdk/constants.py
pypicosdk/error_list.py
pypicosdk/ps6000a.py
pypicosdk/pypicosdk.py
pypicosdk/version.py
pypicosdk_nightly-0.4.0.dist-info/METADATA
pypicosdk_nightly-0.4.0.dist-info/WHEEL
pypicosdk_nightly-0.4.0.dist-info/licenses/LICENSE
pypicosdk_nightly-0.4.0.dist-info/RECORD
