Metadata-Version: 2.4
Name: pypicosdk-nightly
Version: 0.4.0
Summary: Modern Python wrapper for PicoSDK
Project-URL: Documentation, https://jamespicotech.github.io/pyPicoSDK/
Project-URL: github, https://github.com/JamesPicoTech/pyPicoSDK
Author-email: Pico Technology <support@picotech.com>
License: MIT License
License-File: LICENSE
Keywords: electronic,hardware,measurement,test
Classifier: Development Status :: 1 - Planning
Classifier: Operating System :: Microsoft :: Windows
Classifier: Operating System :: Microsoft :: Windows :: Windows 10
Classifier: Operating System :: Microsoft :: Windows :: Windows 11
Classifier: Programming Language :: Python :: 3
Requires-Python: >=3.10
Requires-Dist: numpy
Provides-Extra: test
Requires-Dist: pytest; extra == 'test'
